api_foundry/__init__.py
api_foundry/iac/gateway_spec.py
api_foundry/iac/pulumi/api_foundry.py
api_foundry/scripts/install_secret.py
api_foundry/scripts/postgres_to_openapi.py
api_foundry/utils/app_exception.py
api_foundry/utils/logger.py
api_foundry/utils/model_factory.py
api_foundry/utils/schema_validator.py
api_foundry-0.8.7.dist-info/METADATA
api_foundry-0.8.7.dist-info/WHEEL
api_foundry-0.8.7.dist-info/entry_points.txt
api_foundry-0.8.7.dist-info/licenses/LICENSE
api_foundry-0.8.7.dist-info/RECORD
